ongaku/__init__.py
ongaku/__main__.py
ongaku/builders.py
ongaku/client.py
ongaku/errors.py
ongaku/events.py
ongaku/player.py
ongaku/py.typed
ongaku/rest.py
ongaku/session.py
ongaku/abc/__init__.py
ongaku/abc/errors.py
ongaku/abc/events.py
ongaku/abc/filters.py
ongaku/abc/handler.py
ongaku/abc/info.py
ongaku/abc/player.py
ongaku/abc/playlist.py
ongaku/abc/routeplanner.py
ongaku/abc/session.py
ongaku/abc/statistics.py
ongaku/abc/track.py
ongaku/ext/__init__.py
ongaku/ext/checker/__init__.py
ongaku/ext/checker/abc.py
ongaku/ext/checker/checker.py
ongaku/ext/injection/__init__.py
ongaku/ext/injection/arc.py
ongaku/ext/youtube/__init__.py
ongaku/ext/youtube/endpoints.py
ongaku/impl/__init__.py
ongaku/impl/filters.py
ongaku/impl/handlers.py
ongaku/impl/info.py
ongaku/impl/player.py
ongaku/impl/playlist.py
ongaku/impl/routeplanner.py
ongaku/impl/session.py
ongaku/impl/statistics.py
ongaku/impl/track.py
ongaku/internal/__init__.py
ongaku/internal/about.py
ongaku/internal/converters.py
ongaku/internal/logger.py
ongaku/internal/routes.py
ongaku/internal/types.py
hikari_ongaku-1.0.3.dist-info/LICENSE
hikari_ongaku-1.0.3.dist-info/METADATA
hikari_ongaku-1.0.3.dist-info/WHEEL
hikari_ongaku-1.0.3.dist-info/top_level.txt
hikari_ongaku-1.0.3.dist-info/RECORD
