Metadata-Version: 2.1
Name: hikari-ongaku
Version: 1.0.3
Summary: A simple voice library, for hikari.
Home-page: https://github.com/hikari-ongaku/hikari-ongaku
Author: mplaty
Author-email: contact@mplaty.com
Maintainer: MPlaty
License: MIT
Classifier: Development Status :: 5 - Production/Stable
Classifier: Framework :: AsyncIO
Classifier: Intended Audience :: Developers
Classifier: Natural Language :: English
Classifier: Topic :: Software Development :: Libraries :: Python Modules
Classifier: Programming Language :: Python :: 3.10
Classifier: Programming Language :: Python :: 3.11
Classifier: Programming Language :: Python :: 3.12
Classifier: Programming Language :: Python :: Implementation :: CPython
Classifier: Programming Language :: Python :: 3 :: Only
Classifier: Topic :: Software Development :: Libraries
Classifier: Topic :: Software Development :: Libraries :: Application Frameworks
Classifier: Topic :: Software Development :: Libraries :: Python Modules
Requires-Python: >=3.10.0,<3.13
License-File: LICENSE
Requires-Dist: hikari ~=2.0.0.dev126
Requires-Dist: aiohttp ~=3.10
Provides-Extra: dev
Requires-Dist: nox ==2024.4.15 ; extra == 'dev'
Requires-Dist: hikari ==2.0.0.dev126 ; extra == 'dev'
Provides-Extra: docs
Requires-Dist: black ==24.8.0 ; extra == 'docs'
Requires-Dist: mkdocs ==1.6.0 ; extra == 'docs'
Requires-Dist: mkdocs-autorefs ==1.0.1 ; extra == 'docs'
Requires-Dist: mkdocs-material[imaging] ==9.5.32 ; extra == 'docs'
Requires-Dist: mkdocs-material-extensions ==1.3.1 ; extra == 'docs'
Requires-Dist: mkdocstrings ==0.25.2 ; extra == 'docs'
Requires-Dist: mkdocstrings-python ==1.10.8 ; extra == 'docs'
Requires-Dist: Pygments ==2.18.0 ; extra == 'docs'
Requires-Dist: pymdown-extensions ==10.9 ; extra == 'docs'
Requires-Dist: PyYAML ==6.0.2 ; extra == 'docs'
Requires-Dist: pyyaml-env-tag ==0.1 ; extra == 'docs'
Requires-Dist: Markdown ==3.7 ; extra == 'docs'
Requires-Dist: MarkupSafe ==2.1.5 ; extra == 'docs'
Requires-Dist: mergedeep ==1.3.4 ; extra == 'docs'
Requires-Dist: griffe-inherited-docstrings ==1.0.1 ; extra == 'docs'
Provides-Extra: injection
Requires-Dist: hikari-arc ==1.3.4 ; extra == 'injection'
Requires-Dist: hikari-tanjun ==2.17.5 ; extra == 'injection'
Provides-Extra: speedups
Requires-Dist: aiohttp[speedups] ==3.10.5 ; extra == 'speedups'
Requires-Dist: orjson ==3.10.7 ; extra == 'speedups'
